{"ICAO":"KDFW","IATA":"DFW","name":"Dallas Fort Worth Intl","lat":32.8972,"lon":-97.0377,"elevation":603.9993447501,"regionName":"United States","magneticVariation":3.08091953082057,"runwayCount":7,"runways":[{"ident":"13L","width":200.00000030400003,"length":9010.564318158,"bearing":135.408,"surface":"CONCRETE","markings":["APP"],"lighting":["EDGE","THRESHOLD","REIL-OMNI"],"thresholdOffset":629.9212608,"overrunLength":298.5564309,"ends":[{"ident":"13L","lat":32.9126,"lon":-97.0215},{"ident":"31R","lat":32.9126,"lon":32.895}],"navaids":[]},{"ident":"13R","width":150.984252198,"length":9308.759856669,"bearing":139.183,"surface":"CONCRETE","markings":["PREC-APP"],"lighting":["CENTERLINE","EDGE","THRESHOLD","MALSR","TDZ"],"thresholdOffset":0,"overrunLength":396.98162790000003,"ends":[{"ident":"13R","lat":32.9096,"lon":-97.0832},{"ident":"31L","lat":32.9096,"lon":32.8903}],"navaids":[{"ident":"ILWN","type":"DME","lat":32.8878,"lon":-97.0619,"airport":912214,"runway":"13R","frequency":109500000,"slope":null,"bearing":null,"name":"DME-ILS","elevation":590.0000008968,"range":17.999999984808},{"ident":"OM","type":"OM","lat":32.9723,"lon":-97.146,"airport":912214,"runway":"13R","frequency":null,"slope":null,"bearing":139.185,"name":null,"elevation":607.0013132586,"range":0},{"ident":"ILWN","type":"LOC-ILS","lat":32.8883,"lon":-97.0612,"airport":912214,"runway":"13R","frequency":109500000,"slope":null,"bearing":139.185,"name":"ILS-cat-I","elevation":577.001313213,"range":17.999999984808},{"ident":"MM","type":"MM","lat":32.9153,"lon":-97.0891,"airport":912214,"runway":"13R","frequency":null,"slope":null,"bearing":139.185,"name":null,"elevation":607.0013132586,"range":0},{"ident":"ILWN","type":"GS","lat":32.9067,"lon":-97.0817,"airport":912214,"runway":"13R","frequency":109500000,"slope":3.00139,"bearing":139.37,"name":null,"elevation":588.9993447273,"range":9.999999991560001}]},{"ident":"17C","width":150.984252198,"length":13440.157500744002,"bearing":180.263,"surface":"CONCRETE","markings":["PREC-APP"],"lighting":["CENTERLINE","EDGE","THRESHOLD","ALSF-II"],"thresholdOffset":0,"overrunLength":413.38582740000004,"ends":[{"ident":"17C","lat":32.9157,"lon":-97.026},{"ident":"35C","lat":32.9157,"lon":32.8789}],"navaids":[{"ident":"IFLQ","type":"DME","lat":32.8761,"lon":-97.0277,"airport":912214,"runway":"17C","frequency":110300000,"slope":null,"bearing":null,"name":"DME-ILS","elevation":575.000000874,"range":17.999999984808},{"ident":"OM","type":"OM","lat":32.9957,"lon":-97.0296,"airport":912214,"runway":"17C","frequency":null,"slope":null,"bearing":180.265,"name":null,"elevation":607.0013132586,"range":0},{"ident":"IFLQ","type":"LOC-ILS","lat":32.8759,"lon":-97.0262,"airport":912214,"runway":"17C","frequency":110300000,"slope":null,"bearing":180.265,"name":"ILS-cat-III","elevation":562.9986885198,"range":17.999999984808},{"ident":"IM","type":"IM","lat":32.9178,"lon":-97.026,"airport":912214,"runway":"17C","frequency":null,"slope":null,"bearing":180.265,"name":null,"elevation":607.0013132586,"range":0},{"ident":"MM","type":"MM","lat":32.924,"lon":-97.029,"airport":912214,"runway":"17C","frequency":null,"slope":null,"bearing":180.268,"name":null,"elevation":607.0013132586,"range":0},{"ident":"IFLQ","type":"GS","lat":32.9127,"lon":-97.0247,"airport":912214,"runway":"17C","frequency":110300000,"slope":3.0018,"bearing":180.53,"name":null,"elevation":562.0013131902,"range":9.999999991560001}]},{"ident":"17L","width":150.984252198,"length":8522.900275422002,"bearing":180.252,"surface":"CONCRETE","markings":["PREC-APP"],"lighting":["CENTERLINE","EDGE","THRESHOLD","ALSF-II","TDZ"],"thresholdOffset":0,"overrunLength":400.2624678,"ends":[{"ident":"17L","lat":32.8983,"lon":-97.0098},{"ident":"35R","lat":32.8983,"lon":32.875}],"navaids":[{"ident":"IM","type":"IM","lat":32.9015,"lon":-97.0098,"airport":912214,"runway":"17L","frequency":null,"slope":null,"bearing":180.268,"name":null,"elevation":607.0013132586,"range":0},{"ident":"OM","type":"OM","lat":32.9009,"lon":-97.0114,"airport":912214,"runway":"17L","frequency":null,"slope":null,"bearing":180.268,"name":null,"elevation":607.0013132586,"range":0},{"ident":"MM","type":"MM","lat":32.9067,"lon":-97.0097,"airport":912214,"runway":"17L","frequency":null,"slope":null,"bearing":180.268,"name":null,"elevation":607.0013132586,"range":0},{"ident":"IPPZ","type":"GS","lat":32.8959,"lon":-97.0087,"airport":912214,"runway":"17L","frequency":111750000,"slope":3.0018,"bearing":180.536,"name":null,"elevation":532.0013131446,"range":9.999999991560001},{"ident":"IPPZ","type":"DME","lat":32.9009,"lon":-97.0114,"airport":912214,"runway":"17L","frequency":111750000,"slope":null,"bearing":null,"name":"DME-ILS","elevation":602.9986885806001,"range":17.999999984808},{"ident":"IPPZ","type":"LOC-ILS","lat":32.8721,"lon":-97.0099,"airport":912214,"runway":"17L","frequency":111750000,"slope":null,"bearing":180.268,"name":"ILS-cat-III","elevation":570.0000008664,"range":17.999999984808}]},{"ident":"17R","width":200.00000030400003,"length":13439.402907567,"bearing":180.259,"surface":"CONCRETE","markings":["PREC-APP"],"lighting":["CENTERLINE","EDGE","THRESHOLD","MALSR","TDZ"],"thresholdOffset":0,"overrunLength":400.2624678,"ends":[{"ident":"17R","lat":32.9157,"lon":-97.0299},{"ident":"35L","lat":32.9157,"lon":32.8789}],"navaids":[{"ident":"IJHZ","type":"DME","lat":32.876,"lon":-97.0316,"airport":912214,"runway":"17R","frequency":111350000,"slope":null,"bearing":null,"name":"DME-ILS","elevation":607.0013132586,"range":17.999999984808},{"ident":"OM","type":"OM","lat":32.9957,"lon":-97.0296,"airport":912214,"runway":"17R","frequency":null,"slope":null,"bearing":180.265,"name":null,"elevation":607.0013132586,"range":0},{"ident":"MM","type":"MM","lat":32.924,"lon":-97.029,"airport":912214,"runway":"17R","frequency":null,"slope":null,"bearing":180.259,"name":null,"elevation":607.0013132586,"range":0},{"ident":"IJHZ","type":"GS","lat":32.9127,"lon":-97.0286,"airport":912214,"runway":"17R","frequency":111350000,"slope":3.0018,"bearing":180.518,"name":null,"elevation":567.0013131978001,"range":9.999999991560001},{"ident":"IJHZ","type":"LOC-ILS","lat":32.8761,"lon":-97.0301,"airport":912214,"runway":"17R","frequency":111350000,"slope":null,"bearing":180.259,"name":"ILS-cat-I","elevation":557.9986885122,"range":17.999999984808}]},{"ident":"18L","width":200.00000030400003,"length":13439.238865572,"bearing":180.248,"surface":"CONCRETE","markings":["PREC-APP"],"lighting":["CENTERLINE","EDGE","THRESHOLD","MALSR","TDZ"],"thresholdOffset":0,"overrunLength":403.5433077,"ends":[{"ident":"18L","lat":32.9158,"lon":-97.0508},{"ident":"36R","lat":32.9158,"lon":32.879}],"navaids":[{"ident":"MM","type":"MM","lat":32.9228,"lon":-97.0506,"airport":912214,"runway":"18L","frequency":null,"slope":null,"bearing":180.268,"name":null,"elevation":607.0013132586,"range":0},{"ident":"OM","type":"OM","lat":33.0056,"lon":-97.0542,"airport":912214,"runway":"18L","frequency":null,"slope":null,"bearing":180.25,"name":null,"elevation":607.0013132586,"range":0},{"ident":"ICIX","type":"LOC-ILS","lat":32.8764,"lon":-97.0509,"airport":912214,"runway":"18L","frequency":110550000,"slope":null,"bearing":180.247,"name":"ILS-cat-I","elevation":570.0000008664,"range":17.999999984808},{"ident":"ICIX","type":"GS","lat":32.9128,"lon":-97.0521,"airport":912214,"runway":"18L","frequency":110550000,"slope":3.0018,"bearing":180.494,"name":null,"elevation":593.9993447349,"range":9.999999991560001},{"ident":"ICIX","type":"DME","lat":32.9191,"lon":-97.052,"airport":912214,"runway":"18L","frequency":110550000,"slope":null,"bearing":null,"name":"DME-ILS","elevation":607.0013132586,"range":17.999999984808}]},{"ident":"18R","width":150.984252198,"length":13439.238865572,"bearing":180.251,"surface":"CONCRETE","markings":["PREC-APP"],"lighting":["CENTERLINE","EDGE","THRESHOLD","ALSF-II","TDZ","REIL-OMNI"],"thresholdOffset":0,"overrunLength":403.5433077,"ends":[{"ident":"18R","lat":32.9158,"lon":-97.0547},{"ident":"36L","lat":32.9158,"lon":32.879}],"navaids":[{"ident":"MM","type":"MM","lat":32.9226,"lon":-97.0545,"airport":912214,"runway":"18R","frequency":null,"slope":null,"bearing":180.251,"name":null,"elevation":607.0013132586,"range":0},{"ident":"IVYN","type":"GS","lat":32.9126,"lon":-97.056,"airport":912214,"runway":"18R","frequency":111900000,"slope":3.0018,"bearing":180.502,"name":null,"elevation":601.0006570815,"range":9.999999991560001},{"ident":"IVYN","type":"DME","lat":32.8761,"lon":-97.0535,"airport":912214,"runway":"18R","frequency":111900000,"slope":null,"bearing":null,"name":"DME-ILS","elevation":583.9993447196999,"range":17.999999984808},{"ident":"OM","type":"OM","lat":33.0056,"lon":-97.0542,"airport":912214,"runway":"18R","frequency":null,"slope":null,"bearing":180.251,"name":null,"elevation":607.0013132586,"range":0},{"ident":"IVYN","type":"LOC-ILS","lat":32.8761,"lon":-97.0548,"airport":912214,"runway":"18R","frequency":111900000,"slope":null,"bearing":180.251,"name":"ILS-cat-III","elevation":580.0000008816,"range":17.999999984808},{"ident":"IM","type":"IM","lat":32.9176,"lon":-97.0546,"airport":912214,"runway":"18R","frequency":null,"slope":null,"bearing":180.251,"name":null,"elevation":607.0013132586,"range":0}]},{"ident":"31L","width":150.984252198,"length":9308.759856669,"bearing":319.194,"surface":"CONCRETE","markings":["UK-APP"],"lighting":["CENTERLINE","EDGE","THRESHOLD","REIL-UNI"],"thresholdOffset":0,"overrunLength":400.2624678,"ends":[{"ident":"31L","lat":32.8903,"lon":-97.0633},{"ident":"13R","lat":32.8903,"lon":32.9096}],"navaids":[]},{"ident":"31R","width":200.00000030400003,"length":9010.564318158,"bearing":315.419,"surface":"CONCRETE","markings":["PREC-APP"],"lighting":["EDGE","THRESHOLD","MALSR","TDZ"],"thresholdOffset":0,"overrunLength":298.5564309,"ends":[{"ident":"31R","lat":32.895,"lon":-97.0009},{"ident":"13L","lat":32.895,"lon":32.9126}],"navaids":[{"ident":"IRRA","type":"DME","lat":32.9128,"lon":-97.0229,"airport":912214,"runway":"31R","frequency":110900000,"slope":null,"bearing":null,"name":"DME-ILS","elevation":547.998688497,"range":17.999999984808},{"ident":"OM","type":"OM","lat":32.8309,"lon":-96.9242,"airport":912214,"runway":"31R","frequency":null,"slope":null,"bearing":315.399,"name":null,"elevation":607.0013132586,"range":0},{"ident":"IRRA","type":"LOC-ILS","lat":32.9133,"lon":-97.0223,"airport":912214,"runway":"31R","frequency":110900000,"slope":null,"bearing":315.399,"name":"ILS-cat-I","elevation":552.0013131750001,"range":17.999999984808},{"ident":"MM","type":"MM","lat":32.8891,"lon":-96.9939,"airport":912214,"runway":"31R","frequency":null,"slope":null,"bearing":315.399,"name":null,"elevation":607.0013132586,"range":0},{"ident":"IRRA","type":"GS","lat":32.8977,"lon":-97.0022,"airport":912214,"runway":"31R","frequency":110900000,"slope":3.00315,"bearing":315.798,"name":null,"elevation":512.9986884438,"range":9.999999991560001}]},{"ident":"35C","width":150.984252198,"length":13440.157500744002,"bearing":0.263066,"surface":"CONCRETE","markings":["PREC-APP"],"lighting":["CENTERLINE","EDGE","THRESHOLD","ALSF-II","TDZ","REIL-OMNI"],"thresholdOffset":0,"overrunLength":298.5564309,"ends":[{"ident":"35C","lat":32.8789,"lon":-97.0262},{"ident":"17C","lat":32.8789,"lon":32.9157}],"navaids":[{"ident":"IM","type":"IM","lat":32.8765,"lon":-97.0262,"airport":912214,"runway":"35C","frequency":null,"slope":null,"bearing":0.259,"name":null,"elevation":607.0013132586,"range":0},{"ident":"OM","type":"OM","lat":32.8022,"lon":-97.0275,"airport":912214,"runway":"35C","frequency":null,"slope":null,"bearing":0.259,"name":null,"elevation":607.0013132586,"range":0},{"ident":"IPKQ","type":"GS","lat":32.8818,"lon":-97.0249,"airport":912214,"runway":"35C","frequency":110300000,"slope":3,"bearing":0.518,"name":null,"elevation":562.9986885198,"range":9.999999991560001},{"ident":"MM","type":"MM","lat":32.8712,"lon":-97.0262,"airport":912214,"runway":"35C","frequency":null,"slope":null,"bearing":0.259,"name":null,"elevation":607.0013132586,"range":0},{"ident":"IPKQ","type":"DME","lat":32.8761,"lon":-97.0277,"airport":912214,"runway":"35C","frequency":110300000,"slope":null,"bearing":null,"name":"DME-ILS","elevation":602.9986885806001,"range":17.999999984808},{"ident":"IPKQ","type":"LOC-ILS","lat":32.9186,"lon":-97.026,"airport":912214,"runway":"35C","frequency":110300000,"slope":null,"bearing":0.259,"name":"ILS-cat-III","elevation":557.9986885122,"range":17.999999984808}]},{"ident":"35L","width":200.00000030400003,"length":13439.402907567,"bearing":0.259162,"surface":"CONCRETE","markings":["PREC-APP"],"lighting":["CENTERLINE","EDGE","THRESHOLD","MALSR","TDZ","REIL-OMNI"],"thresholdOffset":0,"overrunLength":400.2624678,"ends":[{"ident":"35L","lat":32.8789,"lon":-97.0301},{"ident":"17R","lat":32.8789,"lon":32.9157}],"navaids":[{"ident":"OM","type":"OM","lat":32.8022,"lon":-97.0275,"airport":912214,"runway":"35L","frequency":null,"slope":null,"bearing":0.259,"name":null,"elevation":607.0013132586,"range":0},{"ident":"IUWX","type":"LOC-ILS","lat":32.9189,"lon":-97.0299,"airport":912214,"runway":"35L","frequency":111350000,"slope":null,"bearing":0.259,"name":"ILS-cat-I","elevation":607.0013132586,"range":17.999999984808},{"ident":"IUWX","type":"GS","lat":32.8819,"lon":-97.0288,"airport":912214,"runway":"35L","frequency":111350000,"slope":3,"bearing":0.518,"name":null,"elevation":563.9993446893001,"range":9.999999991560001},{"ident":"MM","type":"MM","lat":32.8021,"lon":-97.0275,"airport":912214,"runway":"35L","frequency":null,"slope":null,"bearing":0.259,"name":null,"elevation":607.0013132586,"range":0},{"ident":"IUWX","type":"DME","lat":32.876,"lon":-97.0316,"airport":912214,"runway":"35L","frequency":111350000,"slope":null,"bearing":null,"name":"DME-ILS","elevation":607.0013132586,"range":17.999999984808}]},{"ident":"35R","width":150.984252198,"length":8522.900275422002,"bearing":0.251911,"surface":"CONCRETE","markings":["PREC-APP"],"lighting":["CENTERLINE","EDGE","THRESHOLD","ALSF-II","TDZ"],"thresholdOffset":0,"overrunLength":406.8241476,"ends":[{"ident":"35R","lat":32.875,"lon":-97.0099},{"ident":"17L","lat":32.875,"lon":32.8983}],"navaids":[{"ident":"MM","type":"MM","lat":32.8677,"lon":-97.0099,"airport":912214,"runway":"35R","frequency":null,"slope":null,"bearing":0.268,"name":null,"elevation":607.0013132586,"range":0},{"ident":"IAJQ","type":"LOC-ILS","lat":32.9012,"lon":-97.0098,"airport":912214,"runway":"35R","frequency":111750000,"slope":null,"bearing":0.268,"name":"ILS-cat-III","elevation":607.0013132586,"range":17.999999984808},{"ident":"IAJQ","type":"GS","lat":32.8787,"lon":-97.0086,"airport":912214,"runway":"35R","frequency":111750000,"slope":3,"bearing":0.536,"name":null,"elevation":565.0000008588,"range":9.999999991560001},{"ident":"IAJQ","type":"DME","lat":32.9009,"lon":-97.0114,"airport":912214,"runway":"35R","frequency":111750000,"slope":null,"bearing":null,"name":"DME-ILS","elevation":602.9986885806001,"range":17.999999984808},{"ident":"IM","type":"IM","lat":32.8729,"lon":-97.0099,"airport":912214,"runway":"35R","frequency":null,"slope":null,"bearing":0.268,"name":null,"elevation":607.0013132586,"range":0},{"ident":"OM","type":"OM","lat":32.8056,"lon":-97.0074,"airport":912214,"runway":"35R","frequency":null,"slope":null,"bearing":0.268,"name":null,"elevation":607.0013132586,"range":0}]},{"ident":"36L","width":150.984252198,"length":13439.238865572,"bearing":0.250754,"surface":"CONCRETE","markings":["PREC-APP"],"lighting":["CENTERLINE","EDGE","THRESHOLD","MALSR","TDZ","REIL-OMNI"],"thresholdOffset":0,"overrunLength":298.5564309,"ends":[{"ident":"36L","lat":32.879,"lon":-97.0549},{"ident":"18R","lat":32.879,"lon":32.9158}],"navaids":[{"ident":"OM","type":"OM","lat":32.793,"lon":-97.0516,"airport":912214,"runway":"36L","frequency":null,"slope":null,"bearing":0.251,"name":null,"elevation":607.0013132586,"range":0},{"ident":"IBXN","type":"LOC-ILS","lat":32.9186,"lon":-97.0546,"airport":912214,"runway":"36L","frequency":111900000,"slope":null,"bearing":0.251,"name":"ILS-cat-I","elevation":597.9986885730001,"range":17.999999984808},{"ident":"MM","type":"MM","lat":32.8711,"lon":-97.0549,"airport":912214,"runway":"36L","frequency":null,"slope":null,"bearing":0.251,"name":null,"elevation":607.0013132586,"range":0},{"ident":"IBXN","type":"GS","lat":32.8818,"lon":-97.0561,"airport":912214,"runway":"36L","frequency":111900000,"slope":3,"bearing":0.502,"name":null,"elevation":583.9993447196999,"range":9.999999991560001},{"ident":"IBXN","type":"DME","lat":32.8761,"lon":-97.0535,"airport":912214,"runway":"36L","frequency":111900000,"slope":null,"bearing":null,"name":"DME-ILS","elevation":583.9993447196999,"range":17.999999984808},{"ident":"IM","type":"IM","lat":32.8764,"lon":-97.0548,"airport":912214,"runway":"36L","frequency":null,"slope":null,"bearing":0.251,"name":null,"elevation":607.0013132586,"range":0}]},{"ident":"36R","width":200.00000030400003,"length":13439.238865572,"bearing":0.248142,"surface":"CONCRETE","markings":["PREC-APP"],"lighting":["CENTERLINE","EDGE","THRESHOLD","MALSR","TDZ"],"thresholdOffset":0,"overrunLength":393.700788,"ends":[{"ident":"36R","lat":32.879,"lon":-97.0509},{"ident":"18L","lat":32.879,"lon":32.9158}],"navaids":[{"ident":"IFJN","type":"LOC-ILS","lat":32.9186,"lon":-97.0507,"airport":912214,"runway":"36R","frequency":110550000,"slope":null,"bearing":0.247,"name":"ILS-cat-I","elevation":595.0000009044,"range":17.999999984808},{"ident":"MM","type":"MM","lat":32.8714,"lon":-97.051,"airport":912214,"runway":"36R","frequency":null,"slope":null,"bearing":0.247,"name":null,"elevation":607.0013132586,"range":0},{"ident":"IFJN","type":"GS","lat":32.8819,"lon":-97.0522,"airport":912214,"runway":"36R","frequency":110550000,"slope":3,"bearing":0.494,"name":null,"elevation":577.001313213,"range":9.999999991560001},{"ident":"IFJN","type":"DME","lat":32.9191,"lon":-97.052,"airport":912214,"runway":"36R","frequency":110550000,"slope":null,"bearing":null,"name":"DME-ILS","elevation":607.0013132586,"range":17.999999984808},{"ident":"OM","type":"OM","lat":32.793,"lon":-97.0516,"airport":912214,"runway":"36R","frequency":null,"slope":null,"bearing":0.247,"name":null,"elevation":607.0013132586,"range":0}]}],"frequencies":[{"type":"APP","frequency":133520000,"name":"RGNL APP East 3"},{"type":"TWR","frequency":127500000,"name":"RGNL TWR East 2"},{"type":"COM","frequency":122950000,"name":"UNICOM"},{"type":"DEP","frequency":124820000,"name":"RGNL DEP North 1"},{"type":"TWR","frequency":126550000,"name":"RGNL TWR East 1"},{"type":"REC","frequency":135920000,"name":"ATIS Departure"},{"type":"APP","frequency":125020000,"name":"RGNL APP East 1"},{"type":"DEP","frequency":118550000,"name":"RGNL DEP East 1"},{"type":"GND","frequency":121650000,"name":"RGNL GND East 1"},{"type":"REC","frequency":123770000,"name":"ATIS Arrival"},{"type":"GND","frequency":121850000,"name":"RGNL GND West"},{"type":"APP","frequency":119870000,"name":"RGNL APP West 2"},{"type":"TWR","frequency":124150000,"name":"RGNL TWR West 2"},{"type":"DEP","frequency":126470000,"name":"RGNL DEP West 1"},{"type":"CLD","frequency":128250000,"name":"CLNC DEL"},{"type":"TWR","frequency":134900000,"name":"RGNL TWR West 1"},{"type":"DEP","frequency":125120000,"name":"RGNL DEP South 1"},{"type":"GND","frequency":121800000,"name":"RGNL GND East 2"},{"type":"APP","frequency":133620000,"name":"RGNL APP West 1"}]}