{"ICAO":"KTUS","IATA":"TUS","name":"Tucson Intl","lat":32.1169,"lon":-110.942,"elevation":2642.9986916814,"regionName":"United States","magneticVariation":9.490673976071003,"runwayCount":3,"runways":[{"ident":"03","width":150.9186354,"length":7007.677176006,"bearing":44.9087,"surface":"CONCRETE","markings":["PREC-APP"],"lighting":["EDGE","THRESHOLD","ALSF-I"],"thresholdOffset":859.5800538000001,"overrunLength":0,"ends":[{"ident":"03","lat":32.1172,"lon":-110.959},{"ident":"21","lat":32.1172,"lon":32.1308}],"navaids":[]},{"ident":"11L","width":150.9186354,"length":11008.563008859,"bearing":135.17,"surface":"CONCRETE","markings":["PREC-APP"],"lighting":["EDGE","THRESHOLD","MALSR"],"thresholdOffset":0,"overrunLength":3103.6745454,"ends":[{"ident":"11L","lat":32.1234,"lon":-110.948},{"ident":"29R","lat":32.1234,"lon":32.102}],"navaids":[{"ident":"ITUS","type":"LOC-ILS","lat":32.0982,"lon":-110.918,"airport":913806,"runway":"11L","frequency":111700000,"slope":null,"bearing":135.176,"name":"ILS-cat-I","elevation":2660.0000040432,"range":17.999999984808},{"ident":"OM","type":"OM","lat":32.1818,"lon":-111.016,"airport":913806,"runway":"11L","frequency":null,"slope":null,"bearing":135.167,"name":null,"elevation":2642.9986916814,"range":0},{"ident":"MM","type":"MM","lat":32.1311,"lon":-110.956,"airport":913806,"runway":"11L","frequency":null,"slope":null,"bearing":135.167,"name":null,"elevation":2642.9986916814,"range":0},{"ident":"ITUS","type":"DME","lat":32.0982,"lon":-110.918,"airport":913806,"runway":"11L","frequency":111700000,"slope":null,"bearing":null,"name":"DME-ILS","elevation":2660.0000040432,"range":24.9999999789},{"ident":"ITUS","type":"GS","lat":32.1208,"lon":-110.947,"airport":913806,"runway":"11L","frequency":111700000,"slope":3.00135,"bearing":135.334,"name":null,"elevation":2600.000003952,"range":9.999999991560001}]},{"ident":"11R","width":75.000000114,"length":8417.158805445,"bearing":135.161,"surface":"ASPHALT","markings":["PREC-APP"],"lighting":["EDGE","THRESHOLD"],"thresholdOffset":1404.1994772,"overrunLength":0,"ends":[{"ident":"11R","lat":32.1221,"lon":-110.95},{"ident":"29L","lat":32.1221,"lon":32.1058}],"navaids":[]},{"ident":"21","width":150.9186354,"length":7007.677176006,"bearing":224.917,"surface":"CONCRETE","markings":["PREC-APP"],"lighting":["EDGE","THRESHOLD","ALSF-I","REIL-OMNI"],"thresholdOffset":0,"overrunLength":196.850394,"ends":[{"ident":"21","lat":32.1308,"lon":-110.943},{"ident":"03","lat":32.1308,"lon":32.1172}],"navaids":[]},{"ident":"29L","width":75.000000114,"length":8417.158805445,"bearing":315.171,"surface":"ASPHALT","markings":["PREC-APP"],"lighting":["EDGE","THRESHOLD","REIL-OMNI"],"thresholdOffset":0,"overrunLength":0,"ends":[{"ident":"29L","lat":32.1058,"lon":-110.93},{"ident":"11R","lat":32.1058,"lon":32.1221}],"navaids":[]},{"ident":"29R","width":150.9186354,"length":11008.563008859,"bearing":315.183,"surface":"CONCRETE","markings":["PREC-APP"],"lighting":["EDGE","THRESHOLD","MALSR","REIL-OMNI"],"thresholdOffset":0,"overrunLength":1017.060369,"ends":[{"ident":"29R","lat":32.102,"lon":-110.923},{"ident":"11L","lat":32.102,"lon":32.1234}],"navaids":[]}],"frequencies":[{"type":"TWR","frequency":118300000,"name":""},{"type":"CLD","frequency":126650000,"name":"CLNC DEL"},{"type":"APP","frequency":119400000,"name":"APP/DEP"},{"type":"GND","frequency":124400000,"name":""},{"type":"APP","frequency":125100000,"name":"APP/DEP"},{"type":"REC","frequency":123800000,"name":"ATIS"},{"type":"TWR","frequency":119000000,"name":""},{"type":"COM","frequency":122950000,"name":"UNICOM"}]}