{"ICAO":"LMML","IATA":"MLA","name":"Malta Intl","lat":35.8494,"lon":14.4818,"elevation":297.00000045144003,"regionName":"Malta","magneticVariation":3.3306461669985308,"runwayCount":2,"runways":[{"ident":"05","width":147.6377955,"length":7793.766416046,"bearing":54.4037,"surface":"ASPHALT","markings":["APP"],"lighting":["EDGE","THRESHOLD","MALS","REIL-OMNI"],"thresholdOffset":0,"overrunLength":95.14435710000001,"ends":[{"ident":"05","lat":35.8475,"lon":14.4601},{"ident":"23","lat":35.8475,"lon":35.8599}],"navaids":[]},{"ident":"13","width":196.850394,"length":11617.650936294,"bearing":134.872,"surface":"ASPHALT","markings":["PREC-APP"],"lighting":["CENTERLINE","EDGE","THRESHOLD","ALSF-I","REIL-OMNI"],"thresholdOffset":0,"overrunLength":0,"ends":[{"ident":"13","lat":35.8564,"lon":14.4788},{"ident":"31","lat":35.8564,"lon":35.834}],"navaids":[{"ident":"LQ","type":"LOC-ILS","lat":35.8565,"lon":14.4789,"airport":928393,"runway":"13","frequency":109700000,"slope":null,"bearing":134.86,"name":"ILS-cat-II","elevation":299.00000045448,"range":17.999999984808},{"ident":"LQ","type":"GS","lat":35.8565,"lon":14.4789,"airport":928393,"runway":"13","frequency":109700000,"slope":2.85135,"bearing":134.86,"name":null,"elevation":299.00000045448,"range":9.999999991560001}]},{"ident":"23","width":147.6377955,"length":7793.766416046,"bearing":234.416,"surface":"ASPHALT","markings":["APP"],"lighting":["EDGE","THRESHOLD","MALS","REIL-OMNI"],"thresholdOffset":0,"overrunLength":101.7060369,"ends":[{"ident":"23","lat":35.8599,"lon":14.4815},{"ident":"05","lat":35.8599,"lon":35.8475}],"navaids":[]},{"ident":"31","width":196.850394,"length":11617.650936294,"bearing":314.888,"surface":"ASPHALT","markings":["PREC-APP"],"lighting":["CENTERLINE","EDGE","THRESHOLD","ALSF-I","REIL-OMNI"],"thresholdOffset":613.5170613,"overrunLength":177.1653546,"ends":[{"ident":"31","lat":35.834,"lon":14.5067},{"ident":"13","lat":35.834,"lon":35.8564}],"navaids":[{"ident":"LM","type":"LOC-ILS","lat":35.834,"lon":14.5067,"airport":928393,"runway":"31","frequency":110500000,"slope":null,"bearing":314.86,"name":"ILS-cat-I","elevation":299.00000045448,"range":17.999999984808},{"ident":"LM","type":"GS","lat":35.834,"lon":14.5067,"airport":928393,"runway":"31","frequency":110500000,"slope":2.85315,"bearing":314.86,"name":null,"elevation":299.00000045448,"range":9.999999991560001}]}],"frequencies":[{"type":"TWR","frequency":135100000,"name":"Luqa Tower"},{"type":"GND","frequency":121600000,"name":"Luqa Ground"},{"type":"REC","frequency":127400000,"name":"Luqa ATIS"},{"type":"APP","frequency":128150000,"name":"Luqa Approach"}]}