{"id":"3854796541114d29874db2ef630e2196","departure":{"icao":"EDDL","label":"EDDL - Dusseldorf","name":"Dusseldorf"},"destination":{"icao":"EDLP","label":"EDLP - Paderborn Lippstadt","name":"Paderborn Lippstadt"},"aircraft":"Cessna Skyhawk G1000 Asobo","simData":"NAVIGRAPH 2101","navData":"NAVIGRAPH 2101","flightTime":"2021-02-17","mainThumbnail":"main.webp","images":["r00001.webp","r00002.webp","r00003.webp","r00004.webp","r00005.webp","r00006.webp","r00007.webp","r00008.webp","r00009.webp","r00010.webp","r00011.webp"],"flightPlanFile":"3854796541114d29874db2ef630e2196.lnmpln","planType":"IFR","cruiseAlt":"3000","distance":"130 nm","procedures":{"sid":{"name":"LMA1Z","runway":"05R"},"approach":{"name":"FI24","arinc":"I24","runway":"24","type":"ILS","transition":""}},"waypoint":[{"lat":"51.280926","lng":"6.757311","name":"Duesseldorf","ident":"EDDL","alt":"147","region":"ED","procedure":"Departure","airway":"","restrictKt":"","type":"","freq":"","courseM":"","distance":"0.0","wind":"","remarks":"","isProcedure":false},{"lat":"","lng":"","name":"","ident":"RW05R","alt":"147","region":"","procedure":"SID LMA1Z","airway":"Proceed to runway","restrictKt":"147","type":"","freq":"","courseM":"282","distance":"0.1","wind":"228 / 7","remarks":"","isProcedure":true},{"lat":"","lng":"","name":"","ident":"","alt":"886","region":"","procedure":"SID LMA1Z","airway":"Course to altitude","restrictKt":"A 600","type":"","freq":"","courseM":"52","distance":"2.0","wind":"236 / 13","remarks":"","isProcedure":true},{"lat":"","lng":"","name":"","ident":"DL050","alt":"1,998","region":"ED","procedure":"SID LMA1Z","airway":"Direct to fix","restrictKt":"","type":"","freq":"","courseM":"50","distance":"3.0","wind":"249 / 15","remarks":"","isProcedure":true},{"lat":"","lng":"","name":"","ident":"DL051","alt":"2,367","region":"ED","procedure":"SID LMA1Z","airway":"Track to fix","restrictKt":"","type":"","freq":"","courseM":"52","distance":"1.0","wind":"252 / 16","remarks":"Fly over","isProcedure":true},{"lat":"","lng":"","name":"","ident":"DL052","alt":"3,000","region":"ED","procedure":"SID LMA1Z","airway":"Direct to fix","restrictKt":"","type":"","freq":"","courseM":"335","distance":"4.6","wind":"256 / 18","remarks":"Turn left","isProcedure":true},{"lat":"","lng":"","name":"","ident":"LMA","alt":"3,000","region":"ED","procedure":"SID LMA1Z","airway":"Track to fix","restrictKt":"","type":"NDB","freq":"311.0","courseM":"259","distance":"16.7","wind":"253 / 19","remarks":"","isProcedure":true},{"lat":"51.267776","lng":"7.150556","name":"","ident":"DIXAT","alt":"3,000","region":"ED","procedure":"","airway":"","restrictKt":"","type":"","freq":"","courseM":"99","distance":"29","wind":"260 / 17","remarks":"","isProcedure":false},{"lat":"51.515320","lng":"8.074192","name":"","ident":"TINSA","alt":"3,000","region":"ED","procedure":"","airway":"","restrictKt":"","type":"","freq":"","courseM":"63","distance":"38","wind":"264 / 21","remarks":"","isProcedure":false},{"lat":"","lng":"","name":"","ident":"IBEGO (FACF)","alt":"3,000","region":"ED","procedure":"Approach ILS FI24","airway":"Initial fix","restrictKt":"A 3,000","type":"","freq":"","courseM":"66","distance":"29","wind":"262 / 22","remarks":"Related: IPLW / 8.6 nm / 55\u00b0M","isProcedure":true},{"lat":"","lng":"","name":"","ident":"FI24 (FAF)","alt":"1,830","region":"ED","procedure":"Approach ILS FI24","airway":"Course to fix","restrictKt":"GS 1,830","type":"","freq":"","courseM":"234","distance":"3.7","wind":"256 / 20","remarks":"Related: IPLW / 4.9 nm / 55\u00b0M","isProcedure":true},{"lat":"","lng":"","name":"","ident":"RW24 (MAP)","alt":"724","region":"ED","procedure":"Approach ILS FI24","airway":"Course to fix","restrictKt":"724","type":"ILS/DME","freq":"108.55","courseM":"235","distance":"3.4","wind":"250 / 18","remarks":"Related: IPLW / 1.4 nm / 55\u00b0M","isProcedure":true},{"lat":"","lng":"","name":"","ident":"D235B","alt":"","region":"ED","procedure":"Missed ILS FI24","airway":"Course to fix","restrictKt":"","type":"","freq":"","courseM":"233","distance":"2.5","wind":"","remarks":"Fly over, Related: WRB / 21 nm / 283\u00b0M","isProcedure":true},{"lat":"","lng":"","name":"","ident":"PAD","alt":"","region":"ED","procedure":"Missed ILS FI24","airway":"Direct to fix","restrictKt":"3,000","type":"NDB (CL)","freq":"354.0","courseM":"53","distance":"3.0","wind":"","remarks":"Turn right","isProcedure":true},{"lat":"51.614090","lng":"8.616317","name":"Paderborn/Lippstadt","ident":"EDLP","alt":"","region":"ED","procedure":"Destination","airway":"","restrictKt":"","type":"","freq":"","courseM":"","distance":"","wind":"","remarks":"","isProcedure":false}]}