{"id":"576d412ce66c4da59c7098ad13096d4d","departure":{"icao":"LFPG","label":"LFPG - Paris Charles De Gaulle","name":"Paris Charles De Gaulle"},"destination":{"icao":"UNKL","label":"UNKL - Krasnoyarsk Yemelyanovo Intl","name":"Krasnoyarsk Yemelyanovo Intl"},"aircraft":"FlyByWire A32NX","flightTime":"2021-02-14","mainThumbnail":"main.webp","images":["r00001.webp","r00002.webp","r00003.webp","r00004.webp","r00005.webp","r00006.webp","r00007.webp","r00008.webp","r00009.webp","r00010.webp","r00011.webp","r00012.webp","r00013.webp","r00014.webp"],"flightPlanFile":"576d412ce66c4da59c7098ad13096d4d.lnmpln","planType":"IFR","cruiseAlt":"39000","distance":"3,178 nm","procedures":{"sid":{"name":"NURM2L","runway":"08L"},"approach":{"name":"FD29","arinc":"D29","runway":"29","type":"VORDME","transition":"D082I"}},"waypoint":[{"lat":"49.009758","lng":"2.562621","name":"Charles-De-Gaulle","ident":"LFPG","alt":"392","region":"LF","procedure":"Departure","airway":"","restrictKt":"","type":"","freq":"","courseM":"","distance":"0.0","wind":"","remarks":"","isProcedure":false},{"lat":"","lng":"","name":"","ident":"RW08L","alt":"392","region":"","procedure":"SID NURM2L","airway":"Proceed to runway","restrictKt":"392","type":"","freq":"","courseM":"204","distance":"0.9","wind":"128 / 13","remarks":"","isProcedure":true},{"lat":"","lng":"","name":"","ident":"","alt":"1,328","region":"","procedure":"SID NURM2L","airway":"Course to altitude","restrictKt":"A 800","type":"","freq":"","courseM":"85","distance":"2.0","wind":"123 / 11","remarks":"","isProcedure":true},{"lat":"","lng":"","name":"","ident":"PG084","alt":"5,409","region":"LF","procedure":"SID NURM2L","airway":"Course to fix","restrictKt":"","type":"","freq":"","courseM":"84","distance":"8.7","wind":"29 / 6","remarks":"Fly over, Related: PGS / 7.9 nm / 85\u00b0M","isProcedure":true},{"lat":"49.826111","lng":"2.755278","name":"","ident":"NURMO","alt":"28,376","region":"LF","procedure":"SID NURM2L","airway":"Direct to fix","restrictKt":"","type":"","freq":"","courseM":"356","distance":"49","wind":"337 / 67","remarks":"","isProcedure":false},{"lat":"49.912498","lng":"2.840000","name":"","ident":"PERON","alt":"31,248","region":"LF","procedure":"","airway":"UN874 / J","restrictKt":"19,500-50,000","type":"","freq":"","courseM":"31","distance":"6.1","wind":"340 / 74","remarks":"","isProcedure":false},{"lat":"50.000000","lng":"2.925555","name":"","ident":"SULEX","alt":"34,152","region":"LF","procedure":"","airway":"UN874 / J","restrictKt":"19,500-50,000","type":"","freq":"","courseM":"31","distance":"6.2","wind":"346 / 80","remarks":"","isProcedure":false},{"lat":"50.228138","lng":"3.151500","name":"Cambrai Epinoy","ident":"CMB","alt":"39,000","region":"LF","procedure":"","airway":"UN874 / J","restrictKt":"19,500-50,000","type":"VORDME (H)","freq":"112.60","courseM":"32","distance":"16.2","wind":"321 / 55","remarks":"","isProcedure":false},{"lat":"50.404167","lng":"3.275000","name":"","ident":"VEKIN","alt":"39,000","region":"LF","procedure":"","airway":"UN874 / J","restrictKt":"19,500-50,000","type":"","freq":"","courseM":"24","distance":"11.6","wind":"321 / 54","remarks":"","isProcedure":false},{"lat":"50.912640","lng":"3.636972","name":"","ident":"FERDI","alt":"39,000","region":"EB","procedure":"","airway":"","restrictKt":"","type":"","freq":"","courseM":"23","distance":"33","wind":"320 / 50","remarks":"","isProcedure":false},{"lat":"51.235313","lng":"3.869711","name":"","ident":"HELEN","alt":"39,000","region":"EH","procedure":"","airway":"UN873 / J","restrictKt":"19,500","type":"","freq":"","courseM":"23","distance":"21","wind":"321 / 49","remarks":"","isProcedure":false},{"lat":"52.237278","lng":"4.619547","name":"","ident":"EKROS","alt":"39,000","region":"EH","procedure":"","airway":"","restrictKt":"","type":"","freq":"","courseM":"23","distance":"66","wind":"322 / 45","remarks":"","isProcedure":false},{"lat":"52.540279","lng":"4.853781","name":"Spijkerboor","ident":"SPY","alt":"39,000","region":"EH","procedure":"","airway":"UN873 / J","restrictKt":"20,000","type":"VORDME (H)","freq":"113.30","courseM":"25","distance":"20","wind":"324 / 44","remarks":"","isProcedure":false},{"lat":"52.688141","lng":"5.162553","name":"","ident":"BETUS","alt":"39,000","region":"EH","procedure":"","airway":"UN873 / J","restrictKt":"21,000","type":"","freq":"","courseM":"52","distance":"14.3","wind":"325 / 43","remarks":"","isProcedure":false},{"lat":"52.739403","lng":"5.270489","name":"","ident":"ANDIK","alt":"39,000","region":"EH","procedure":"","airway":"UN873 / J","restrictKt":"21,000","type":"","freq":"","courseM":"50","distance":"5.0","wind":"324 / 43","remarks":"","isProcedure":false},{"lat":"52.782452","lng":"5.361492","name":"","ident":"KEKIX","alt":"39,000","region":"EH","procedure":"","airway":"UN873 / J","restrictKt":"21,000","type":"","freq":"","courseM":"50","distance":"4.2","wind":"324 / 43","remarks":"","isProcedure":false},{"lat":"53.105469","lng":"6.054969","name":"","ident":"GRONY","alt":"39,000","region":"EH","procedure":"","airway":"UN873 / J","restrictKt":"21,000","type":"","freq":"","courseM":"50","distance":"32","wind":"328 / 42","remarks":"","isProcedure":false},{"lat":"53.348171","lng":"6.588867","name":"","ident":"BEDUM","alt":"39,000","region":"EH","procedure":"","airway":"UN873 / J","restrictKt":"21,000","type":"","freq":"","courseM":"50","distance":"24","wind":"329 / 43","remarks":"","isProcedure":false},{"lat":"53.495834","lng":"6.816483","name":"","ident":"LABIL","alt":"39,000","region":"EH","procedure":"","airway":"UN873 / J","restrictKt":"21,000","type":"","freq":"","courseM":"40","distance":"12.0","wind":"329 / 44","remarks":"","isProcedure":false},{"lat":"53.562702","lng":"6.920028","name":"","ident":"JUIST","alt":"39,000","region":"ED","procedure":"","airway":"UN873 / J","restrictKt":"24,500","type":"","freq":"","courseM":"40","distance":"5.5","wind":"329 / 44","remarks":"","isProcedure":false},{"lat":"53.678055","lng":"6.996667","name":"","ident":"NIRDU","alt":"39,000","region":"ED","procedure":"","airway":"UN873 / J","restrictKt":"24,500","type":"","freq":"","courseM":"19","distance":"7.4","wind":"329 / 44","remarks":"","isProcedure":false},{"lat":"54.298332","lng":"7.415833","name":"","ident":"WELGO","alt":"39,000","region":"ED","procedure":"","airway":"UN873 / J","restrictKt":"24,500","type":"","freq":"","courseM":"19","distance":"40","wind":"330 / 46","remarks":"","isProcedure":false},{"lat":"55.224998","lng":"8.032500","name":"","ident":"INSUS","alt":"39,000","region":"EK","procedure":"","airway":"","restrictKt":"","type":"","freq":"","courseM":"18","distance":"60","wind":"329 / 49","remarks":"","isProcedure":false},{"lat":"55.415001","lng":"8.166389","name":"","ident":"MIKRO","alt":"39,000","region":"EK","procedure":"","airway":"N873 / B","restrictKt":"9,500","type":"","freq":"","courseM":"19","distance":"12.3","wind":"329 / 49","remarks":"","isProcedure":false},{"lat":"55.603054","lng":"8.300000","name":"","ident":"BAVTA","alt":"39,000","region":"EK","procedure":"","airway":"N873 / B","restrictKt":"9,500","type":"","freq":"","courseM":"19","distance":"12.2","wind":"329 / 49","remarks":"","isProcedure":false},{"lat":"56.065556","lng":"9.118889","name":"","ident":"GIKIV","alt":"39,000","region":"EK","procedure":"","airway":"N873 / B","restrictKt":"9,500","type":"","freq":"","courseM":"41","distance":"39","wind":"329 / 49","remarks":"","isProcedure":false},{"lat":"56.226387","lng":"9.411389","name":"","ident":"INTET","alt":"39,000","region":"EK","procedure":"","airway":"N873 / B","restrictKt":"9,500","type":"","freq":"","courseM":"42","distance":"13.7","wind":"330 / 49","remarks":"","isProcedure":false},{"lat":"56.541668","lng":"9.995000","name":"","ident":"RADIS","alt":"39,000","region":"EK","procedure":"","airway":"N873 / B","restrictKt":"9,500","type":"","freq":"","courseM":"42","distance":"27","wind":"331 / 50","remarks":"","isProcedure":false},{"lat":"58.169388","lng":"13.294306","name":"","ident":"LABAN","alt":"39,000","region":"ES","procedure":"","airway":"","restrictKt":"","type":"","freq":"","courseM":"41","distance":"145","wind":"327 / 46","remarks":"","isProcedure":false},{"lat":"58.599998","lng":"14.264361","name":"","ident":"DETSO","alt":"39,000","region":"ES","procedure":"","airway":"N873 / B","restrictKt":"9,500","type":"","freq":"","courseM":"44","distance":"40","wind":"329 / 45","remarks":"","isProcedure":false},{"lat":"59.200417","lng":"15.687805","name":"","ident":"PELIT","alt":"39,000","region":"ES","procedure":"","airway":"N873 / B","restrictKt":"9,500","type":"","freq":"","courseM":"44","distance":"57","wind":"334 / 44","remarks":"","isProcedure":false},{"lat":"59.412445","lng":"16.211971","name":"","ident":"TORVA","alt":"39,000","region":"ES","procedure":"","airway":"N873 / B","restrictKt":"9,500","type":"","freq":"","courseM":"45","distance":"20","wind":"335 / 44","remarks":"","isProcedure":false},{"lat":"59.586193","lng":"16.650389","name":"Aros","ident":"ARS","alt":"39,000","region":"ES","procedure":"","airway":"N873 / B","restrictKt":"9,500","type":"VORDME (H)","freq":"112.80","courseM":"48","distance":"16.9","wind":"337 / 43","remarks":"","isProcedure":false},{"lat":"59.724529","lng":"17.411694","name":"","ident":"LINSA","alt":"39,000","region":"ES","procedure":"","airway":"N873 / B","restrictKt":"9,500","type":"","freq":"","courseM":"66","distance":"25","wind":"337 / 41","remarks":"","isProcedure":false},{"lat":"60.288887","lng":"20.623888","name":"","ident":"SOTUP","alt":"39,000","region":"EF","procedure":"","airway":"","restrictKt":"","type":"","freq":"","courseM":"61","distance":"102","wind":"332 / 34","remarks":"","isProcedure":false},{"lat":"60.474998","lng":"21.367777","name":"","ident":"OTKIL","alt":"39,000","region":"EF","procedure":"","airway":"N88 / B","restrictKt":"9,500","type":"","freq":"","courseM":"55","distance":"25","wind":"329 / 33","remarks":"","isProcedure":false},{"lat":"60.637501","lng":"22.029167","name":"","ident":"IPDUR","alt":"39,000","region":"EF","procedure":"","airway":"N88 / B","restrictKt":"9,500","type":"","freq":"","courseM":"54","distance":"22","wind":"328 / 31","remarks":"","isProcedure":false},{"lat":"60.688889","lng":"22.241667","name":"","ident":"XETNI","alt":"39,000","region":"EF","procedure":"","airway":"N88 / B","restrictKt":"9,500","type":"","freq":"","courseM":"55","distance":"7.0","wind":"328 / 30","remarks":"","isProcedure":false},{"lat":"62.188889","lng":"29.677778","name":"","ident":"ETOBA","alt":"39,000","region":"EF","procedure":"","airway":"N88 / J","restrictKt":"28,500","type":"","freq":"","courseM":"52","distance":"231","wind":"303 / 15","remarks":"","isProcedure":false},{"lat":"62.421665","lng":"31.108334","name":"","ident":"KOMEK","alt":"39,000","region":"EF","procedure":"","airway":"N87 / J","restrictKt":"28,500","type":"","freq":"","courseM":"57","distance":"42","wind":"293 / 15","remarks":"","isProcedure":false},{"lat":"63.700279","lng":"45.339169","name":"","ident":"PINEG","alt":"39,000","region":"UL","procedure":"","airway":"","restrictKt":"","type":"","freq":"","courseM":"54","distance":"394","wind":"229 / 38","remarks":"","isProcedure":false},{"lat":"62.467224","lng":"66.031670","name":"","ident":"SORLI","alt":"39,000","region":"US","procedure":"","airway":"","restrictKt":"","type":"","freq":"","courseM":"68","distance":"565","wind":"251 / 63","remarks":"","isProcedure":false},{"lat":"62.327221","lng":"67.721664","name":"","ident":"ABGIL","alt":"39,000","region":"US","procedure":"","airway":"G716 / B","restrictKt":"6,000-53,000","type":"","freq":"","courseM":"80","distance":"48","wind":"255 / 64","remarks":"","isProcedure":false},{"lat":"61.995556","lng":"70.970276","name":"","ident":"LARTU","alt":"39,000","region":"US","procedure":"","airway":"G716 / B","restrictKt":"6,000-53,000","type":"","freq":"","courseM":"82","distance":"93","wind":"262 / 65","remarks":"","isProcedure":false},{"lat":"61.937222","lng":"71.386948","name":"","ident":"NEGNA","alt":"39,000","region":"US","procedure":"","airway":"G716 / B","restrictKt":"6,000-53,000","type":"","freq":"","courseM":"88","distance":"12.3","wind":"263 / 65","remarks":"","isProcedure":false},{"lat":"61.783333","lng":"72.446663","name":"","ident":"OGIKA","alt":"39,000","region":"US","procedure":"","airway":"G716 / B","restrictKt":"6,000-53,000","type":"","freq":"","courseM":"89","distance":"31","wind":"266 / 65","remarks":"","isProcedure":false},{"lat":"61.500557","lng":"74.248611","name":"","ident":"ULGUN","alt":"39,000","region":"US","procedure":"","airway":"G716 / B","restrictKt":"6,000-53,000","type":"","freq":"","courseM":"91","distance":"54","wind":"269 / 66","remarks":"","isProcedure":false},{"lat":"61.287224","lng":"75.135559","name":"","ident":"APRAN","alt":"39,000","region":"US","procedure":"","airway":"G716 / B","restrictKt":"6,000-53,000","type":"","freq":"","courseM":"100","distance":"29","wind":"272 / 66","remarks":"","isProcedure":false},{"lat":"61.156387","lng":"75.652496","name":"","ident":"TETSI","alt":"39,000","region":"US","procedure":"","airway":"G716 / B","restrictKt":"6,000-53,000","type":"","freq":"","courseM":"101","distance":"16.9","wind":"273 / 66","remarks":"","isProcedure":false},{"lat":"60.943974","lng":"76.467781","name":"Nizhnevartovsk","ident":"NJC","alt":"39,000","region":"US","procedure":"","airway":"G716 / B","restrictKt":"6,000-53,000","type":"VORDME (H)","freq":"112.30","courseM":"103","distance":"27","wind":"277 / 68","remarks":"","isProcedure":false},{"lat":"60.833889","lng":"77.033890","name":"","ident":"PAROM","alt":"39,000","region":"US","procedure":"","airway":"R496 / B","restrictKt":"6,000-53,000","type":"","freq":"","courseM":"97","distance":"17.8","wind":"279 / 68","remarks":"","isProcedure":false},{"lat":"60.710556","lng":"77.658890","name":"","ident":"SOREB","alt":"39,000","region":"UN","procedure":"","airway":"R496 / B","restrictKt":"6,000-51,000","type":"","freq":"","courseM":"97","distance":"19.8","wind":"280 / 69","remarks":"","isProcedure":false},{"lat":"60.178890","lng":"80.382500","name":"","ident":"SOTIM","alt":"39,000","region":"UN","procedure":"","airway":"R496 / B","restrictKt":"15,000-51,000","type":"","freq":"","courseM":"97","distance":"87","wind":"287 / 68","remarks":"","isProcedure":false},{"lat":"58.640556","lng":"86.730003","name":"Maksimkin Yar","ident":"CE","alt":"39,000","region":"UN","procedure":"","airway":"R496 / B","restrictKt":"15,000-51,000","type":"NDB","freq":"510.0","courseM":"104","distance":"215","wind":"299 / 63","remarks":"","isProcedure":false},{"lat":"58.205555","lng":"88.029442","name":"","ident":"RONIK","alt":"39,000","region":"UN","procedure":"","airway":"R496 / B","restrictKt":"18,000-51,000","type":"","freq":"","courseM":"115","distance":"48","wind":"302 / 62","remarks":"","isProcedure":false},{"lat":"57.718887","lng":"89.406113","name":"","ident":"NOVRA","alt":"39,000","region":"UN","procedure":"","airway":"R496 / B","restrictKt":"18,000-53,000","type":"","freq":"","courseM":"117","distance":"53","wind":"304 / 61","remarks":"","isProcedure":false},{"lat":"57.050556","lng":"92.533058","name":"","ident":"DEBAR","alt":"17,507","region":"UN","procedure":"","airway":"B805 / B","restrictKt":"11,000-53,000","type":"","freq":"","courseM":"106","distance":"109","wind":"304 / 78","remarks":"","isProcedure":false},{"lat":"56.641109","lng":"92.653336","name":"Gorevoye","ident":"GO","alt":"11,759","region":"UN","procedure":"","airway":"G809 / B","restrictKt":"20,000-53,000","type":"NDB","freq":"1,061.0","courseM":"167","distance":"25","wind":"294 / 47","remarks":"","isProcedure":false},{"lat":"56.162998","lng":"92.536163","name":"Krasnoyarsk","ident":"KRS","alt":"5,071","region":"UN","procedure":"","airway":"G809 / B","restrictKt":"20,000-53,000","type":"VORDME (H)","freq":"113.20","courseM":"184","distance":"29","wind":"281 / 21","remarks":"","isProcedure":false},{"lat":"","lng":"","name":"","ident":"D082I","alt":"2,920","region":"UN","procedure":"Transition D082I","airway":"Initial fix","restrictKt":"2,920","type":"","freq":"","courseM":"82","distance":"9.3","wind":"272 / 13","remarks":"","isProcedure":true},{"lat":"","lng":"","name":"","ident":"CD29","alt":"2,920","region":"UN","procedure":"Transition D082I","airway":"Course to fix","restrictKt":"2,920","type":"","freq":"","courseM":"199","distance":"4.3","wind":"273 / 13","remarks":"Related: KRS / 8.4 nm / 110\u00b0M","isProcedure":true},{"lat":"","lng":"","name":"","ident":"CD29 (FACF)","alt":"2,920","region":"UN","procedure":"Approach VORDME FD29","airway":"Initial fix","restrictKt":"2,920","type":"","freq":"","courseM":"","distance":"0.0","wind":"","remarks":"Related: KRS / 8.4 nm / 110\u00b0M","isProcedure":true},{"lat":"","lng":"","name":"","ident":"FD29 (FAF)","alt":"2,920","region":"UN","procedure":"Approach VORDME FD29","airway":"Course to fix","restrictKt":"2,920","type":"","freq":"","courseM":"291","distance":"2.8","wind":"272 / 13","remarks":"Related: KRS / 5.5 nm / 109\u00b0M","isProcedure":true},{"lat":"","lng":"","name":"","ident":"18VOR","alt":"1,730","region":"UN","procedure":"Approach VORDME FD29","airway":"Course to fix","restrictKt":"A 1,730","type":"","freq":"","courseM":"289","distance":"3.7","wind":"258 / 9","remarks":"Related: KRS / 1.8 nm / 109\u00b0M","isProcedure":true},{"lat":"","lng":"","name":"","ident":"MD29 (MAP)","alt":"1,447","region":"UN","procedure":"Approach VORDME FD29","airway":"Course to fix","restrictKt":"1,447","type":"","freq":"","courseM":"289","distance":"0.9","wind":"253 / 9","remarks":"Related: KRS / 0.9 nm / 109\u00b0M","isProcedure":true},{"lat":"","lng":"","name":"","ident":"RW29","alt":"992","region":"","procedure":"Approach VORDME FD29","airway":"Straight in","restrictKt":"992","type":"","freq":"","courseM":"289","distance":"1.4","wind":"243 / 8","remarks":"","isProcedure":true},{"lat":"","lng":"","name":"","ident":"","alt":"","region":"","procedure":"Missed VORDME FD29","airway":"Course to altitude","restrictKt":"A 1,930","type":"","freq":"","courseM":"289","distance":"2.0","wind":"","remarks":"","isProcedure":true},{"lat":"","lng":"","name":"","ident":"D082I","alt":"","region":"UN","procedure":"Missed VORDME FD29","airway":"Course to fix","restrictKt":"2,920","type":"","freq":"","courseM":"109","distance":"14.2","wind":"","remarks":"Turn right, Related: KRS / 9.4 nm / 82\u00b0M","isProcedure":true},{"lat":"56.172962","lng":"92.493187","name":"Yemelyanovo","ident":"UNKL","alt":"","region":"UN","procedure":"Destination","airway":"","restrictKt":"","type":"","freq":"","courseM":"","distance":"","wind":"","remarks":"","isProcedure":false}]}